mimory_mcp_focus_langchain/__init__.py
mimory_mcp_focus_langchain/client.py
mimory_mcp_focus_langchain-0.1.0.dist-info/licenses/LICENSE
mimory_mcp_focus_langchain-0.1.0.dist-info/METADATA
mimory_mcp_focus_langchain-0.1.0.dist-info/WHEEL
mimory_mcp_focus_langchain-0.1.0.dist-info/top_level.txt
mimory_mcp_focus_langchain-0.1.0.dist-info/RECORD
