Metadata-Version: 2.4
Name: mimory-mcp-focus-langchain
Version: 0.1.0
Summary: LangChain integration for mimory-mcp-focus
Author-email: Travis McQueen <oss@mimory.io>
License: MIT
Project-URL: Homepage, https://github.com/mimoryinc/mimory-mcp-focus-langchain
Project-URL: Repository, https://github.com/mimoryinc/mimory-mcp-focus-langchain
Project-URL: Bug Tracker, https://github.com/mimoryinc/mimory-mcp-focus-langchain/issues
Keywords: mcp,langchain,focus,ai,tools
Classifier: Intended Audience :: Developers
Classifier: License :: OSI Approved :: MIT License
Classifier: Programming Language :: Python :: 3.10
Classifier: Programming Language :: Python :: 3.11
Classifier: Programming Language :: Python :: 3.12
Classifier: Topic :: Software Development :: Libraries :: Python Modules
Classifier: Topic :: Scientific/Engineering :: Artificial Intelligence
Requires-Python: >=3.10
License-File: LICENSE
Requires-Dist: mimory-mcp-focus>=0.1.0
Requires-Dist: langchain-mcp-adapters>=0.1.11
Requires-Dist: langchain-core>=0.3.0
Requires-Dist: langgraph>=0.1.0
Requires-Dist: pydantic>=2.0.0
Requires-Dist: pyjwt>=2.0.0
Provides-Extra: dev
Requires-Dist: pytest>=7.0.0; extra == "dev"
Requires-Dist: pytest-asyncio>=0.21.0; extra == "dev"
Requires-Dist: black>=23.0.0; extra == "dev"
Requires-Dist: isort>=5.12.0; extra == "dev"
Requires-Dist: mypy>=1.0.0; extra == "dev"
Requires-Dist: ruff>=0.1.0; extra == "dev"
Dynamic: license-file
